spyrograph/__init__.py
spyrograph/core/__init__.py
spyrograph/core/_cycloid.py
spyrograph/core/_misc.py
spyrograph/core/_trochoid.py
spyrograph/epitrochoid/__init__.py
spyrograph/epitrochoid/epicycloid.py
spyrograph/epitrochoid/epitrochoid.py
spyrograph/epitrochoid/special/__init__.py
spyrograph/epitrochoid/special/cardioid.py
spyrograph/epitrochoid/special/nephroid.py
spyrograph/epitrochoid/special/ranuncloid.py
spyrograph/hypotrochoid/__init__.py
spyrograph/hypotrochoid/hypocycloid.py
spyrograph/hypotrochoid/hypotrochoid.py
spyrograph/hypotrochoid/special/__init__.py
spyrograph/hypotrochoid/special/astroid.py
spyrograph/hypotrochoid/special/deltoid.py
spyrograph/hypotrochoid/special/ellipse.py
spyrograph/hypotrochoid/special/tusi_couple.py
tests/__init__.py
tests/_cycloid.py
tests/_trochoid.py
tests/test_cycloid.py
tests/test_misc.py
tests/test_trochoid.py
spyrograph-0.29.0.dist-info/LICENSE
spyrograph-0.29.0.dist-info/METADATA
spyrograph-0.29.0.dist-info/WHEEL
spyrograph-0.29.0.dist-info/top_level.txt
spyrograph-0.29.0.dist-info/RECORD
