Metadata-Version: 2.1
Name: spyrograph
Version: 0.29.0
Summary: Library for drawing spirographs in Python
Home-page: https://github.com/chris-greening/spyrograph
Author: Chris Greening
Author-email: chris@christophergreening.com
Classifier: Programming Language :: Python :: 3
Classifier: License :: OSI Approved :: MIT License
Classifier: Operating System :: OS Independent
Requires-Python: >=3.7
License-File: LICENSE
Requires-Dist: numpy
